pytest_libfaketime/__init__.py
pytest_libfaketime-0.1.3.dist-info/LICENSE
pytest_libfaketime-0.1.3.dist-info/METADATA
pytest_libfaketime-0.1.3.dist-info/WHEEL
pytest_libfaketime-0.1.3.dist-info/entry_points.txt
pytest_libfaketime-0.1.3.dist-info/RECORD
